funfedi_schema/__init__.py
funfedi_schema/__main__.py
funfedi_schema/activity_pub_object.py
funfedi_schema/result.py
funfedi_schema/test_activity_pub_object.py
funfedi_schema/test_result.py
funfedi_schema/schema/__init__.py
funfedi_schema/schema/activity-pub-object.schema.json
funfedi_schema/schema/test_load.py
funfedi_schema-0.1.0.dist-info/METADATA
funfedi_schema-0.1.0.dist-info/WHEEL
funfedi_schema-0.1.0.dist-info/entry_points.txt
funfedi_schema-0.1.0.dist-info/RECORD
