Metadata-Version: 2.4
Name: funfedi_schema
Version: 0.1.0
Summary: Add your description here
Requires-Python: >=3.12
Requires-Dist: click>=8.1.7
Requires-Dist: dictdiffer>=0.9.0
Requires-Dist: griffe-fieldz>=0.4.0
Requires-Dist: hatch>=1.16.2
Requires-Dist: jsonschema>=4.25.1
Requires-Dist: mkdocstrings-python>=2.0.1
Requires-Dist: pyld>=2.0.4
Requires-Dist: requests>=2.32.3
